Metadata-Version: 2.1
Name: the-money-converter
Version: 1.0.0
Summary: 货币汇率转换
Author: GetDream_1996
Author-email: 543046534@qq.com
Requires-Python: >=3.0
License-File: LICENSE
